gfsopt/__init__.py
gfsopt/gfsopt.py
gfsopt/main.py
gfsopt-1.1.0.dist-info/LICENSE
gfsopt-1.1.0.dist-info/METADATA
gfsopt-1.1.0.dist-info/WHEEL
gfsopt-1.1.0.dist-info/top_level.txt
gfsopt-1.1.0.dist-info/RECORD
