Metadata-Version: 2.1
Name: gfsopt
Version: 1.1.0
Summary: Scaffolding for the Global Function Search optimizer from Dlib
Home-page: https://github.com/tsoernes/gfsopt
Author: Torstein Soernes
Author-email: t.soernes@gmail.com
License: UNKNOWN
Project-URL: Documentation, http://gfsopt.readthedocs.io/
Platform: UNKNOWN
Classifier: Programming Language :: Python :: 3
Classifier: License :: OSI Approved :: MIT License
Classifier: Operating System :: OS Independent
Requires-Python: >=3.6
Requires-Dist: numpy
Requires-Dist: dlib
Requires-Dist: datadiff
